[
    {
        "Year": "2013",
        "Interest Amount": 498817992842.70013,
        "Inventory Amount": 141378565719866.09
    },
    {
        "Year": "2014",
        "Interest Amount": 482849982087.75006,
        "Inventory Amount": 127088702083330.92
    },
    {
        "Year": "2015",
        "Interest Amount": 454915518988.36029,
        "Inventory Amount": 108986697806382.86
    },
    {
        "Year": "2016",
        "Interest Amount": 903994110785.19019,
        "Inventory Amount": 162449788223870.13
    },
    {
        "Year": "2017",
        "Interest Amount": 1439885478051.1096,
        "Inventory Amount": 196998475211707.13
    }
]